mweather/__init__.py
mweather/__pycache__/__init__.cpython-312.pyc
mweather-1.2.dist-info/METADATA
mweather-1.2.dist-info/WHEEL
mweather-1.2.dist-info/top_level.txt
mweather-1.2.dist-info/RECORD
