Metadata-Version: 2.1
Name: mweather
Version: 1.2
Summary: Бесплатное и быстрое api для получения погоды.
Author: mc.c0rp
Author-email: mc.c0rp@icloud.com
Classifier: Programming Language :: Python :: 3
Classifier: License :: OSI Approved :: MIT License
Classifier: Operating System :: OS Independent
Requires-Python: >=3.6
